PhpShejimoshiFanli/README.md
PhpShejimoshiFanli/__init__.py
PhpShejimoshiFanli/__main__.py
PhpShejimoshiFanli/file.epub
PhpShejimoshiFanli/index.html
PhpShejimoshiFanli/css/__init__.py
PhpShejimoshiFanli/css/annotations.css
PhpShejimoshiFanli/css/main.css
PhpShejimoshiFanli/css/normalize.css
PhpShejimoshiFanli/css/popup.css
PhpShejimoshiFanli/font/__init__.py
PhpShejimoshiFanli/font/fontello.eot
PhpShejimoshiFanli/font/fontello.svg
PhpShejimoshiFanli/font/fontello.ttf
PhpShejimoshiFanli/font/fontello.woff
PhpShejimoshiFanli/img/__init__.py
PhpShejimoshiFanli/img/annotator-glyph-sprite.png
PhpShejimoshiFanli/img/annotator-icon-sprite.png
PhpShejimoshiFanli/img/apple-touch-icon.png
PhpShejimoshiFanli/img/cancelfullscreen.png
PhpShejimoshiFanli/img/close.png
PhpShejimoshiFanli/img/fullscreen.png
PhpShejimoshiFanli/img/loader.gif
PhpShejimoshiFanli/img/menu-icon.png
PhpShejimoshiFanli/img/save.png
PhpShejimoshiFanli/img/saved.png
PhpShejimoshiFanli/img/settings-s.png
PhpShejimoshiFanli/img/settings.png
PhpShejimoshiFanli/img/star.png
PhpShejimoshiFanli/js/__init__.py
PhpShejimoshiFanli/js/epub.js
PhpShejimoshiFanli/js/epub.min.js
PhpShejimoshiFanli/js/epub.min.map
PhpShejimoshiFanli/js/hooks.min.js
PhpShejimoshiFanli/js/hooks.min.map
PhpShejimoshiFanli/js/reader.js
PhpShejimoshiFanli/js/reader.js.map
PhpShejimoshiFanli/js/reader.min.js
PhpShejimoshiFanli/js/reader.min.map
PhpShejimoshiFanli/js/hooks/__init__.py
PhpShejimoshiFanli/js/hooks/extensions/__init__.py
PhpShejimoshiFanli/js/hooks/extensions/highlight.js
PhpShejimoshiFanli/js/libs/__init__.py
PhpShejimoshiFanli/js/libs/jquery.min.js
PhpShejimoshiFanli/js/libs/localforage.min.js
PhpShejimoshiFanli/js/libs/screenfull.js
PhpShejimoshiFanli/js/libs/screenfull.min.js
PhpShejimoshiFanli/js/libs/zip.min.js
PhpShejimoshiFanli/js/plugins/__init__.py
PhpShejimoshiFanli/js/plugins/hypothesis.js
PhpShejimoshiFanli/js/plugins/search.js
php_shejimoshi_fanli-2024.3.2.0.dist-info/METADATA
php_shejimoshi_fanli-2024.3.2.0.dist-info/WHEEL
php_shejimoshi_fanli-2024.3.2.0.dist-info/entry_points.txt
php_shejimoshi_fanli-2024.3.2.0.dist-info/top_level.txt
php_shejimoshi_fanli-2024.3.2.0.dist-info/RECORD
